logontg/__init__.py
logontg/client.py
logontg-1.0.1.dist-info/licenses/LICENSE
logontg-1.0.1.dist-info/METADATA
logontg-1.0.1.dist-info/WHEEL
logontg-1.0.1.dist-info/top_level.txt
logontg-1.0.1.dist-info/RECORD
